<?xml version="1.0" encoding="UTF-8"?>

<configuration experimentType="microarray_1colour_mrna_differential" r_data="1">
    <analytics>
        <array_design>A-AFFY-44</array_design>
        <assay_groups>
            <assay_group id="g1" label="none; normal">
                <assay>GSM534163</assay>
                <assay>GSM534191</assay>
                <assay>GSM534200</assay>
                <assay>GSM534151</assay>
                <assay>GSM534166</assay>
                <assay>GSM533996</assay>
                <assay>GSM534072</assay>
                <assay>GSM533981</assay>
                <assay>GSM534167</assay>
                <assay>GSM533954</assay>
                <assay>GSM534116</assay>
                <assay>GSM534046</assay>
                <assay>GSM534096</assay>
                <assay>GSM533941</assay>
                <assay>GSM534145</assay>
                <assay>GSM534137</assay>
                <assay>GSM534049</assay>
                <assay>GSM534003</assay>
                <assay>GSM533953</assay>
                <assay>GSM534068</assay>
                <assay>GSM533992</assay>
                <assay>GSM533971</assay>
                <assay>GSM534080</assay>
                <assay>GSM533946</assay>
                <assay>GSM534077</assay>
                <assay>GSM533928</assay>
                <assay>GSM533999</assay>
                <assay>GSM533924</assay>
                <assay>GSM534051</assay>
                <assay>GSM534185</assay>
                <assay>GSM533986</assay>
                <assay>GSM534159</assay>
                <assay>GSM533998</assay>
                <assay>GSM534168</assay>
                <assay>GSM534071</assay>
                <assay>GSM534131</assay>
                <assay>GSM533944</assay>
                <assay>GSM534013</assay>
                <assay>GSM534135</assay>
                <assay>GSM534144</assay>
                <assay>GSM534004</assay>
                <assay>GSM534147</assay>
                <assay>GSM533984</assay>
                <assay>GSM534186</assay>
                <assay>GSM534098</assay>
                <assay>GSM534025</assay>
                <assay>GSM534132</assay>
                <assay>GSM534143</assay>
                <assay>GSM533972</assay>
                <assay>GSM534052</assay>
                <assay>GSM534107</assay>
                <assay>GSM533962</assay>
                <assay>GSM534076</assay>
                <assay>GSM534128</assay>
                <assay>GSM534150</assay>
                <assay>GSM534133</assay>
                <assay>GSM534084</assay>
                <assay>GSM533982</assay>
                <assay>GSM534198</assay>
                <assay>GSM534011</assay>
                <assay>GSM533939</assay>
                <assay>GSM534156</assay>
                <assay>GSM534012</assay>
                <assay>GSM534169</assay>
                <assay>GSM534058</assay>
                <assay>GSM533960</assay>
                <assay>GSM534053</assay>
                <assay>GSM533966</assay>
                <assay>GSM534101</assay>
                <assay>GSM534188</assay>
                <assay>GSM534172</assay>
                <assay>GSM533974</assay>
                <assay>GSM534117</assay>
                <assay>GSM533940</assay>
                <assay>GSM534027</assay>
                <assay>GSM534125</assay>
                <assay>GSM533932</assay>
                <assay>GSM534202</assay>
                <assay>GSM534057</assay>
                <assay>GSM534045</assay>
                <assay>GSM534102</assay>
                <assay>GSM534178</assay>
                <assay>GSM533969</assay>
                <assay>GSM534134</assay>
                <assay>GSM533943</assay>
                <assay>GSM534047</assay>
                <assay>GSM534127</assay>
                <assay>GSM534100</assay>
                <assay>GSM534136</assay>
                <assay>GSM534138</assay>
                <assay>GSM534031</assay>
                <assay>GSM533991</assay>
                <assay>GSM534181</assay>
                <assay>GSM534044</assay>
                <assay>GSM533934</assay>
                <assay>GSM534035</assay>
                <assay>GSM534146</assay>
                <assay>GSM533949</assay>
                <assay>GSM534192</assay>
                <assay>GSM534093</assay>
                <assay>GSM534155</assay>
                <assay>GSM534153</assay>
                <assay>GSM534164</assay>
                <assay>GSM534089</assay>
                <assay>GSM534119</assay>
                <assay>GSM533947</assay>
                <assay>GSM533929</assay>
                <assay>GSM534126</assay>
                <assay>GSM534030</assay>
                <assay>GSM534141</assay>
                <assay>GSM533987</assay>
                <assay>GSM533942</assay>
                <assay>GSM533938</assay>
                <assay>GSM534149</assay>
                <assay>GSM534000</assay>
                <assay>GSM534129</assay>
                <assay>GSM533933</assay>
                <assay>GSM534124</assay>
                <assay>GSM533968</assay>
                <assay>GSM533948</assay>
                <assay>GSM534029</assay>
                <assay>GSM534123</assay>
                <assay>GSM534074</assay>
                <assay>GSM534139</assay>
                <assay>GSM533921</assay>
                <assay>GSM533983</assay>
                <assay>GSM534114</assay>
                <assay>GSM534189</assay>
                <assay>GSM534148</assay>
                <assay>GSM533922</assay>
                <assay>GSM534105</assay>
                <assay>GSM534081</assay>
                <assay>GSM534194</assay>
                <assay>GSM534042</assay>
                <assay>GSM533985</assay>
                <assay>GSM534197</assay>
                <assay>GSM534113</assay>
                <assay>GSM534021</assay>
                <assay>GSM534048</assay>
                <assay>GSM534103</assay>
                <assay>GSM534059</assay>
                <assay>GSM534097</assay>
                <assay>GSM533979</assay>
                <assay>GSM534060</assay>
                <assay>GSM534038</assay>
                <assay>GSM534066</assay>
                <assay>GSM534140</assay>
                <assay>GSM534022</assay>
                <assay>GSM534069</assay>
                <assay>GSM533930</assay>
                <assay>GSM534015</assay>
                <assay>GSM534179</assay>
                <assay>GSM533970</assay>
                <assay>GSM534017</assay>
                <assay>GSM534085</assay>
                <assay>GSM534088</assay>
                <assay>GSM533965</assay>
                <assay>GSM533945</assay>
                <assay>GSM534002</assay>
                <assay>GSM533950</assay>
                <assay>GSM534037</assay>
                <assay>GSM534118</assay>
                <assay>GSM533958</assay>
                <assay>GSM534104</assay>
                <assay>GSM534201</assay>
                <assay>GSM534019</assay>
                <assay>GSM534040</assay>
                <assay>GSM533997</assay>
                <assay>GSM534079</assay>
                <assay>GSM534142</assay>
                <assay>GSM534122</assay>
                <assay>GSM534099</assay>
                <assay>GSM533961</assay>
                <assay>GSM534041</assay>
                <assay>GSM533925</assay>
            </assay_group>
            <assay_group id="g2" label="none; transplant failure">
                <assay>GSM534078</assay>
                <assay>GSM534111</assay>
                <assay>GSM534161</assay>
                <assay>GSM534034</assay>
                <assay>GSM533973</assay>
                <assay>GSM534157</assay>
                <assay>GSM533967</assay>
                <assay>GSM534086</assay>
                <assay>GSM534083</assay>
                <assay>GSM534050</assay>
                <assay>GSM534061</assay>
                <assay>GSM534065</assay>
                <assay>GSM534165</assay>
                <assay>GSM534091</assay>
                <assay>GSM533993</assay>
                <assay>GSM534018</assay>
                <assay>GSM534177</assay>
                <assay>GSM534067</assay>
                <assay>GSM534054</assay>
                <assay>GSM534082</assay>
                <assay>GSM534056</assay>
                <assay>GSM534160</assay>
                <assay>GSM534173</assay>
                <assay>GSM534006</assay>
                <assay>GSM533923</assay>
                <assay>GSM533994</assay>
                <assay>GSM534036</assay>
                <assay>GSM534073</assay>
                <assay>GSM534026</assay>
                <assay>GSM534075</assay>
            </assay_group>
            <assay_group id="g3" label="transplant rejection; normal">
                <assay>GSM534195</assay>
                <assay>GSM534007</assay>
                <assay>GSM533978</assay>
                <assay>GSM533936</assay>
                <assay>GSM534152</assay>
                <assay>GSM534087</assay>
                <assay>GSM534130</assay>
                <assay>GSM534171</assay>
                <assay>GSM534120</assay>
                <assay>GSM533989</assay>
                <assay>GSM534028</assay>
                <assay>GSM534032</assay>
                <assay>GSM533926</assay>
                <assay>GSM534190</assay>
                <assay>GSM534162</assay>
                <assay>GSM534170</assay>
                <assay>GSM534184</assay>
                <assay>GSM533976</assay>
                <assay>GSM533977</assay>
                <assay>GSM534024</assay>
                <assay>GSM534183</assay>
                <assay>GSM533975</assay>
                <assay>GSM534010</assay>
                <assay>GSM534182</assay>
                <assay>GSM533927</assay>
                <assay>GSM534196</assay>
                <assay>GSM534023</assay>
                <assay>GSM533931</assay>
                <assay>GSM534014</assay>
                <assay>GSM534193</assay>
                <assay>GSM534064</assay>
                <assay>GSM534112</assay>
                <assay>GSM534020</assay>
                <assay>GSM533935</assay>
                <assay>GSM534094</assay>
                <assay>GSM534158</assay>
                <assay>GSM534154</assay>
                <assay>GSM534039</assay>
                <assay>GSM534115</assay>
                <assay>GSM534001</assay>
                <assay>GSM534055</assay>
                <assay>GSM534016</assay>
                <assay>GSM534176</assay>
                <assay>GSM534033</assay>
                <assay>GSM533990</assay>
                <assay>GSM534180</assay>
                <assay>GSM533957</assay>
                <assay>GSM533988</assay>
                <assay>GSM534199</assay>
                <assay>GSM534095</assay>
                <assay>GSM533937</assay>
                <assay>GSM534106</assay>
                <assay>GSM533980</assay>
                <assay>GSM534121</assay>
                <assay>GSM533959</assay>
            </assay_group>
            <assay_group id="g4" label="transplant rejection; transplant failure">
                <assay>GSM534043</assay>
                <assay>GSM534005</assay>
                <assay>GSM534063</assay>
                <assay>GSM533995</assay>
                <assay>GSM533952</assay>
                <assay>GSM533956</assay>
                <assay>GSM534070</assay>
                <assay>GSM533963</assay>
                <assay>GSM534108</assay>
                <assay>GSM534175</assay>
                <assay>GSM534187</assay>
                <assay>GSM534110</assay>
                <assay>GSM533951</assay>
                <assay>GSM534008</assay>
                <assay>GSM534009</assay>
                <assay>GSM534092</assay>
                <assay>GSM534062</assay>
                <assay>GSM533964</assay>
                <assay>GSM533955</assay>
                <assay>GSM534109</assay>
                <assay>GSM534174</assay>
            </assay_group>
        </assay_groups>
        <contrasts>
            <contrast id="g1_g2" cttv_primary="0">
                <name>'transplant failure' vs 'normal' in 'none'</name>
                <reference_assay_group>g1</reference_assay_group>
                <test_assay_group>g2</test_assay_group>
                <batch_effects>
                    <batch_effect name="sample included in analysis">
                        <batch value="sample OK">
                            <assay>GSM534085</assay>
                            <assay>GSM533940</assay>
                            <assay>GSM533941</assay>
                            <assay>GSM534046</assay>
                            <assay>GSM533922</assay>
                            <assay>GSM534037</assay>
                            <assay>GSM534179</assay>
                            <assay>GSM534142</assay>
                            <assay>GSM534138</assay>
                            <assay>GSM533942</assay>
                            <assay>GSM533986</assay>
                            <assay>GSM533972</assay>
                            <assay>GSM534167</assay>
                            <assay>GSM534143</assay>
                            <assay>GSM534116</assay>
                            <assay>GSM534146</assay>
                            <assay>GSM533999</assay>
                            <assay>GSM534072</assay>
                            <assay>GSM534137</assay>
                            <assay>GSM534088</assay>
                            <assay>GSM534091</assay>
                            <assay>GSM534149</assay>
                            <assay>GSM534107</assay>
                            <assay>GSM534066</assay>
                            <assay>GSM533991</assay>
                            <assay>GSM534117</assay>
                            <assay>GSM534021</assay>
                            <assay>GSM534041</assay>
                            <assay>GSM534077</assay>
                            <assay>GSM533930</assay>
                            <assay>GSM534051</assay>
                            <assay>GSM534185</assay>
                            <assay>GSM534044</assay>
                            <assay>GSM533996</assay>
                            <assay>GSM534073</assay>
                            <assay>GSM533965</assay>
                            <assay>GSM534038</assay>
                            <assay>GSM534164</assay>
                            <assay>GSM534025</assay>
                            <assay>GSM534004</assay>
                            <assay>GSM533994</assay>
                            <assay>GSM534096</assay>
                            <assay>GSM534104</assay>
                            <assay>GSM534155</assay>
                            <assay>GSM534139</assay>
                            <assay>GSM534012</assay>
                            <assay>GSM534097</assay>
                            <assay>GSM534022</assay>
                            <assay>GSM534126</assay>
                            <assay>GSM534099</assay>
                            <assay>GSM534047</assay>
                            <assay>GSM534144</assay>
                            <assay>GSM534151</assay>
                            <assay>GSM533961</assay>
                            <assay>GSM534052</assay>
                            <assay>GSM534156</assay>
                            <assay>GSM533987</assay>
                            <assay>GSM534186</assay>
                            <assay>GSM534161</assay>
                            <assay>GSM534192</assay>
                            <assay>GSM534076</assay>
                            <assay>GSM534168</assay>
                            <assay>GSM534089</assay>
                            <assay>GSM534150</assay>
                            <assay>GSM534000</assay>
                            <assay>GSM534031</assay>
                            <assay>GSM534093</assay>
                            <assay>GSM534122</assay>
                            <assay>GSM534029</assay>
                            <assay>GSM534058</assay>
                            <assay>GSM534098</assay>
                            <assay>GSM533925</assay>
                            <assay>GSM533921</assay>
                            <assay>GSM534057</assay>
                            <assay>GSM534071</assay>
                            <assay>GSM534101</assay>
                            <assay>GSM534103</assay>
                            <assay>GSM534200</assay>
                            <assay>GSM534163</assay>
                            <assay>GSM534194</assay>
                            <assay>GSM534191</assay>
                            <assay>GSM534181</assay>
                            <assay>GSM534145</assay>
                            <assay>GSM534036</assay>
                            <assay>GSM534060</assay>
                            <assay>GSM534084</assay>
                            <assay>GSM534017</assay>
                            <assay>GSM534169</assay>
                            <assay>GSM534048</assay>
                            <assay>GSM534100</assay>
                            <assay>GSM534124</assay>
                            <assay>GSM533934</assay>
                            <assay>GSM534086</assay>
                            <assay>GSM534131</assay>
                            <assay>GSM534128</assay>
                            <assay>GSM533969</assay>
                            <assay>GSM534053</assay>
                            <assay>GSM534111</assay>
                            <assay>GSM533970</assay>
                            <assay>GSM534003</assay>
                            <assay>GSM534019</assay>
                            <assay>GSM534119</assay>
                            <assay>GSM534153</assay>
                            <assay>GSM534127</assay>
                            <assay>GSM534018</assay>
                            <assay>GSM534069</assay>
                            <assay>GSM534113</assay>
                            <assay>GSM534061</assay>
                            <assay>GSM534118</assay>
                            <assay>GSM534134</assay>
                            <assay>GSM534201</assay>
                            <assay>GSM534013</assay>
                            <assay>GSM533943</assay>
                            <assay>GSM534172</assay>
                            <assay>GSM534141</assay>
                            <assay>GSM533939</assay>
                            <assay>GSM534050</assay>
                            <assay>GSM534059</assay>
                            <assay>GSM534030</assay>
                            <assay>GSM534049</assay>
                            <assay>GSM534102</assay>
                            <assay>GSM533962</assay>
                            <assay>GSM533966</assay>
                            <assay>GSM534135</assay>
                            <assay>GSM533960</assay>
                            <assay>GSM533979</assay>
                            <assay>GSM533981</assay>
                            <assay>GSM534189</assay>
                            <assay>GSM534035</assay>
                        </batch>
                        <batch value="sample rejected">
                            <assay>GSM534067</assay>
                            <assay>GSM533998</assay>
                            <assay>GSM534165</assay>
                            <assay>GSM534178</assay>
                            <assay>GSM534147</assay>
                            <assay>GSM533924</assay>
                            <assay>GSM534078</assay>
                            <assay>GSM534197</assay>
                            <assay>GSM533983</assay>
                            <assay>GSM533938</assay>
                            <assay>GSM534114</assay>
                            <assay>GSM534042</assay>
                            <assay>GSM534040</assay>
                            <assay>GSM533944</assay>
                            <assay>GSM534132</assay>
                            <assay>GSM534105</assay>
                            <assay>GSM533968</assay>
                            <assay>GSM534079</assay>
                            <assay>GSM534026</assay>
                            <assay>GSM533993</assay>
                            <assay>GSM534054</assay>
                            <assay>GSM534082</assay>
                            <assay>GSM534198</assay>
                            <assay>GSM533946</assay>
                            <assay>GSM534157</assay>
                            <assay>GSM534027</assay>
                            <assay>GSM534068</assay>
                            <assay>GSM534015</assay>
                            <assay>GSM534173</assay>
                            <assay>GSM533933</assay>
                            <assay>GSM533974</assay>
                            <assay>GSM534159</assay>
                            <assay>GSM534166</assay>
                            <assay>GSM533929</assay>
                            <assay>GSM533947</assay>
                            <assay>GSM534034</assay>
                            <assay>GSM534123</assay>
                            <assay>GSM534148</assay>
                            <assay>GSM534045</assay>
                            <assay>GSM534177</assay>
                            <assay>GSM533971</assay>
                            <assay>GSM533982</assay>
                            <assay>GSM533958</assay>
                            <assay>GSM534080</assay>
                            <assay>GSM534129</assay>
                            <assay>GSM533954</assay>
                            <assay>GSM534133</assay>
                            <assay>GSM533950</assay>
                            <assay>GSM534136</assay>
                            <assay>GSM533949</assay>
                            <assay>GSM534083</assay>
                            <assay>GSM534006</assay>
                            <assay>GSM534202</assay>
                            <assay>GSM533984</assay>
                            <assay>GSM533948</assay>
                            <assay>GSM533967</assay>
                            <assay>GSM534074</assay>
                            <assay>GSM534075</assay>
                            <assay>GSM534056</assay>
                            <assay>GSM534188</assay>
                            <assay>GSM534011</assay>
                            <assay>GSM533928</assay>
                            <assay>GSM533973</assay>
                            <assay>GSM533932</assay>
                            <assay>GSM533953</assay>
                            <assay>GSM534125</assay>
                            <assay>GSM533923</assay>
                            <assay>GSM534002</assay>
                            <assay>GSM533997</assay>
                            <assay>GSM534081</assay>
                            <assay>GSM534140</assay>
                            <assay>GSM533945</assay>
                            <assay>GSM533992</assay>
                            <assay>GSM534065</assay>
                            <assay>GSM533985</assay>
                            <assay>GSM534160</assay>
                        </batch>
                    </batch_effect>
                </batch_effects>
            </contrast>
            <contrast id="g1_g3" cttv_primary="0">
                <name>'transplant rejection' vs 'none' in 'normal'</name>
                <reference_assay_group>g1</reference_assay_group>
                <test_assay_group>g3</test_assay_group>
                <batch_effects>
                    <batch_effect name="sample included in analysis">
                        <batch value="sample OK">
                            <assay>GSM534134</assay>
                            <assay>GSM534112</assay>
                            <assay>GSM533990</assay>
                            <assay>GSM534201</assay>
                            <assay>GSM533943</assay>
                            <assay>GSM534013</assay>
                            <assay>GSM534141</assay>
                            <assay>GSM534172</assay>
                            <assay>GSM533939</assay>
                            <assay>GSM534059</assay>
                            <assay>GSM534024</assay>
                            <assay>GSM534049</assay>
                            <assay>GSM534030</assay>
                            <assay>GSM533962</assay>
                            <assay>GSM534055</assay>
                            <assay>GSM534102</assay>
                            <assay>GSM534028</assay>
                            <assay>GSM533966</assay>
                            <assay>GSM534135</assay>
                            <assay>GSM533979</assay>
                            <assay>GSM533960</assay>
                            <assay>GSM534106</assay>
                            <assay>GSM534195</assay>
                            <assay>GSM534001</assay>
                            <assay>GSM534035</assay>
                            <assay>GSM534095</assay>
                            <assay>GSM533981</assay>
                            <assay>GSM534189</assay>
                            <assay>GSM534100</assay>
                            <assay>GSM534124</assay>
                            <assay>GSM533934</assay>
                            <assay>GSM534171</assay>
                            <assay>GSM534131</assay>
                            <assay>GSM534128</assay>
                            <assay>GSM533969</assay>
                            <assay>GSM534053</assay>
                            <assay>GSM533970</assay>
                            <assay>GSM534003</assay>
                            <assay>GSM534119</assay>
                            <assay>GSM534019</assay>
                            <assay>GSM533980</assay>
                            <assay>GSM534007</assay>
                            <assay>GSM534184</assay>
                            <assay>GSM534153</assay>
                            <assay>GSM534127</assay>
                            <assay>GSM534069</assay>
                            <assay>GSM534113</assay>
                            <assay>GSM534118</assay>
                            <assay>GSM534032</assay>
                            <assay>GSM533921</assay>
                            <assay>GSM534057</assay>
                            <assay>GSM534071</assay>
                            <assay>GSM534101</assay>
                            <assay>GSM534152</assay>
                            <assay>GSM534014</assay>
                            <assay>GSM533957</assay>
                            <assay>GSM534103</assay>
                            <assay>GSM534200</assay>
                            <assay>GSM534163</assay>
                            <assay>GSM534158</assay>
                            <assay>GSM534194</assay>
                            <assay>GSM534145</assay>
                            <assay>GSM534181</assay>
                            <assay>GSM534191</assay>
                            <assay>GSM534084</assay>
                            <assay>GSM534060</assay>
                            <assay>GSM534017</assay>
                            <assay>GSM534169</assay>
                            <assay>GSM534048</assay>
                            <assay>GSM534156</assay>
                            <assay>GSM534190</assay>
                            <assay>GSM534186</assay>
                            <assay>GSM533987</assay>
                            <assay>GSM533926</assay>
                            <assay>GSM534192</assay>
                            <assay>GSM534168</assay>
                            <assay>GSM534076</assay>
                            <assay>GSM534089</assay>
                            <assay>GSM534150</assay>
                            <assay>GSM534000</assay>
                            <assay>GSM534031</assay>
                            <assay>GSM534122</assay>
                            <assay>GSM534093</assay>
                            <assay>GSM534023</assay>
                            <assay>GSM534029</assay>
                            <assay>GSM534098</assay>
                            <assay>GSM534058</assay>
                            <assay>GSM533925</assay>
                            <assay>GSM534130</assay>
                            <assay>GSM534012</assay>
                            <assay>GSM534139</assay>
                            <assay>GSM534097</assay>
                            <assay>GSM533977</assay>
                            <assay>GSM534022</assay>
                            <assay>GSM534126</assay>
                            <assay>GSM534099</assay>
                            <assay>GSM534182</assay>
                            <assay>GSM534196</assay>
                            <assay>GSM533937</assay>
                            <assay>GSM534047</assay>
                            <assay>GSM534144</assay>
                            <assay>GSM534183</assay>
                            <assay>GSM533961</assay>
                            <assay>GSM534151</assay>
                            <assay>GSM534052</assay>
                            <assay>GSM534180</assay>
                            <assay>GSM534117</assay>
                            <assay>GSM533978</assay>
                            <assay>GSM534021</assay>
                            <assay>GSM534077</assay>
                            <assay>GSM534041</assay>
                            <assay>GSM534051</assay>
                            <assay>GSM533930</assay>
                            <assay>GSM534094</assay>
                            <assay>GSM534193</assay>
                            <assay>GSM534185</assay>
                            <assay>GSM534044</assay>
                            <assay>GSM533996</assay>
                            <assay>GSM533965</assay>
                            <assay>GSM533976</assay>
                            <assay>GSM534025</assay>
                            <assay>GSM534004</assay>
                            <assay>GSM534164</assay>
                            <assay>GSM534038</assay>
                            <assay>GSM534033</assay>
                            <assay>GSM534096</assay>
                            <assay>GSM534120</assay>
                            <assay>GSM534104</assay>
                            <assay>GSM534155</assay>
                            <assay>GSM534072</assay>
                            <assay>GSM534137</assay>
                            <assay>GSM534088</assay>
                            <assay>GSM534107</assay>
                            <assay>GSM534066</assay>
                            <assay>GSM534149</assay>
                            <assay>GSM533991</assay>
                            <assay>GSM533989</assay>
                            <assay>GSM534085</assay>
                            <assay>GSM533940</assay>
                            <assay>GSM533935</assay>
                            <assay>GSM534046</assay>
                            <assay>GSM533941</assay>
                            <assay>GSM534179</assay>
                            <assay>GSM534037</assay>
                            <assay>GSM533922</assay>
                            <assay>GSM534142</assay>
                            <assay>GSM533986</assay>
                            <assay>GSM533942</assay>
                            <assay>GSM534138</assay>
                            <assay>GSM534143</assay>
                            <assay>GSM534167</assay>
                            <assay>GSM533972</assay>
                            <assay>GSM534146</assay>
                            <assay>GSM534116</assay>
                            <assay>GSM533999</assay>
                        </batch>
                        <batch value="sample rejected">
                            <assay>GSM533946</assay>
                            <assay>GSM534027</assay>
                            <assay>GSM534198</assay>
                            <assay>GSM534079</assay>
                            <assay>GSM534132</assay>
                            <assay>GSM533944</assay>
                            <assay>GSM534105</assay>
                            <assay>GSM533968</assay>
                            <assay>GSM533988</assay>
                            <assay>GSM533975</assay>
                            <assay>GSM533938</assay>
                            <assay>GSM534114</assay>
                            <assay>GSM534042</assay>
                            <assay>GSM534040</assay>
                            <assay>GSM533924</assay>
                            <assay>GSM534197</assay>
                            <assay>GSM533983</assay>
                            <assay>GSM533998</assay>
                            <assay>GSM534178</assay>
                            <assay>GSM534147</assay>
                            <assay>GSM533971</assay>
                            <assay>GSM534148</assay>
                            <assay>GSM534045</assay>
                            <assay>GSM534199</assay>
                            <assay>GSM533947</assay>
                            <assay>GSM534115</assay>
                            <assay>GSM534010</assay>
                            <assay>GSM534123</assay>
                            <assay>GSM533936</assay>
                            <assay>GSM534016</assay>
                            <assay>GSM533929</assay>
                            <assay>GSM534176</assay>
                            <assay>GSM533974</assay>
                            <assay>GSM534162</assay>
                            <assay>GSM534166</assay>
                            <assay>GSM534159</assay>
                            <assay>GSM534015</assay>
                            <assay>GSM533933</assay>
                            <assay>GSM534068</assay>
                            <assay>GSM534188</assay>
                            <assay>GSM534011</assay>
                            <assay>GSM533928</assay>
                            <assay>GSM534121</assay>
                            <assay>GSM533948</assay>
                            <assay>GSM534074</assay>
                            <assay>GSM534154</assay>
                            <assay>GSM533949</assay>
                            <assay>GSM534202</assay>
                            <assay>GSM533984</assay>
                            <assay>GSM533950</assay>
                            <assay>GSM534136</assay>
                            <assay>GSM533954</assay>
                            <assay>GSM534133</assay>
                            <assay>GSM533982</assay>
                            <assay>GSM533958</assay>
                            <assay>GSM534129</assay>
                            <assay>GSM534080</assay>
                            <assay>GSM534064</assay>
                            <assay>GSM533985</assay>
                            <assay>GSM533945</assay>
                            <assay>GSM533992</assay>
                            <assay>GSM534140</assay>
                            <assay>GSM534039</assay>
                            <assay>GSM533927</assay>
                            <assay>GSM534081</assay>
                            <assay>GSM534087</assay>
                            <assay>GSM533953</assay>
                            <assay>GSM534020</assay>
                            <assay>GSM534125</assay>
                            <assay>GSM534002</assay>
                            <assay>GSM534170</assay>
                            <assay>GSM533997</assay>
                            <assay>GSM533959</assay>
                            <assay>GSM533931</assay>
                            <assay>GSM533932</assay>
                        </batch>
                    </batch_effect>
                </batch_effects>
            </contrast>
            <contrast id="g2_g4" cttv_primary="0">
                <name>'transplant rejection' vs 'none' in 'transplant failure'</name>
                <reference_assay_group>g2</reference_assay_group>
                <test_assay_group>g4</test_assay_group>
                <batch_effects>
                    <batch_effect name="sample included in analysis">
                        <batch value="sample OK">
                            <assay>GSM534092</assay>
                            <assay>GSM534063</assay>
                            <assay>GSM534070</assay>
                            <assay>GSM534161</assay>
                            <assay>GSM534108</assay>
                            <assay>GSM534086</assay>
                            <assay>GSM533952</assay>
                            <assay>GSM534050</assay>
                            <assay>GSM534111</assay>
                            <assay>GSM534043</assay>
                            <assay>GSM534091</assay>
                            <assay>GSM534175</assay>
                            <assay>GSM534110</assay>
                            <assay>GSM534073</assay>
                            <assay>GSM534036</assay>
                            <assay>GSM534062</assay>
                            <assay>GSM534061</assay>
                            <assay>GSM534009</assay>
                            <assay>GSM533956</assay>
                            <assay>GSM533994</assay>
                            <assay>GSM534018</assay>
                        </batch>
                        <batch value="sample rejected">
                            <assay>GSM533993</assay>
                            <assay>GSM534026</assay>
                            <assay>GSM533967</assay>
                            <assay>GSM534054</assay>
                            <assay>GSM534082</assay>
                            <assay>GSM534034</assay>
                            <assay>GSM534075</assay>
                            <assay>GSM533963</assay>
                            <assay>GSM534056</assay>
                            <assay>GSM534065</assay>
                            <assay>GSM534005</assay>
                            <assay>GSM534187</assay>
                            <assay>GSM534177</assay>
                            <assay>GSM534157</assay>
                            <assay>GSM534160</assay>
                            <assay>GSM534067</assay>
                            <assay>GSM533973</assay>
                            <assay>GSM534008</assay>
                            <assay>GSM534165</assay>
                            <assay>GSM534173</assay>
                            <assay>GSM534078</assay>
                            <assay>GSM533995</assay>
                            <assay>GSM533923</assay>
                            <assay>GSM534174</assay>
                            <assay>GSM533951</assay>
                            <assay>GSM534083</assay>
                            <assay>GSM533955</assay>
                            <assay>GSM534006</assay>
                            <assay>GSM533964</assay>
                            <assay>GSM534109</assay>
                        </batch>
                    </batch_effect>
                </batch_effects>
            </contrast>
            <contrast id="g3_g4" cttv_primary="0">
                <name>'transplant failure' vs 'normal' in 'transplant rejection'</name>
                <reference_assay_group>g3</reference_assay_group>
                <test_assay_group>g4</test_assay_group>
                <batch_effects>
                    <batch_effect name="sample included in analysis">
                        <batch value="sample OK">
                            <assay>GSM533935</assay>
                            <assay>GSM534094</assay>
                            <assay>GSM534193</assay>
                            <assay>GSM533926</assay>
                            <assay>GSM533978</assay>
                            <assay>GSM534092</assay>
                            <assay>GSM534171</assay>
                            <assay>GSM534070</assay>
                            <assay>GSM534180</assay>
                            <assay>GSM534190</assay>
                            <assay>GSM534130</assay>
                            <assay>GSM534009</assay>
                            <assay>GSM534120</assay>
                            <assay>GSM534007</assay>
                            <assay>GSM534175</assay>
                            <assay>GSM534184</assay>
                            <assay>GSM534033</assay>
                            <assay>GSM534023</assay>
                            <assay>GSM533980</assay>
                            <assay>GSM533976</assay>
                            <assay>GSM534024</assay>
                            <assay>GSM534055</assay>
                            <assay>GSM533952</assay>
                            <assay>GSM534158</assay>
                            <assay>GSM533957</assay>
                            <assay>GSM534063</assay>
                            <assay>GSM533977</assay>
                            <assay>GSM534152</assay>
                            <assay>GSM534108</assay>
                            <assay>GSM534014</assay>
                            <assay>GSM534032</assay>
                            <assay>GSM534112</assay>
                            <assay>GSM533990</assay>
                            <assay>GSM534183</assay>
                            <assay>GSM534001</assay>
                            <assay>GSM534095</assay>
                            <assay>GSM533989</assay>
                            <assay>GSM534106</assay>
                            <assay>GSM534195</assay>
                            <assay>GSM533956</assay>
                            <assay>GSM534196</assay>
                            <assay>GSM534043</assay>
                            <assay>GSM533937</assay>
                            <assay>GSM534110</assay>
                            <assay>GSM534182</assay>
                            <assay>GSM534062</assay>
                            <assay>GSM534028</assay>
                        </batch>
                        <batch value="sample rejected">
                            <assay>GSM534064</assay>
                            <assay>GSM534005</assay>
                            <assay>GSM534121</assay>
                            <assay>GSM534199</assay>
                            <assay>GSM534187</assay>
                            <assay>GSM533963</assay>
                            <assay>GSM533936</assay>
                            <assay>GSM534115</assay>
                            <assay>GSM534010</assay>
                            <assay>GSM533927</assay>
                            <assay>GSM534154</assay>
                            <assay>GSM534039</assay>
                            <assay>GSM534016</assay>
                            <assay>GSM534087</assay>
                            <assay>GSM533988</assay>
                            <assay>GSM534109</assay>
                            <assay>GSM533955</assay>
                            <assay>GSM533964</assay>
                            <assay>GSM534176</assay>
                            <assay>GSM534170</assay>
                            <assay>GSM534174</assay>
                            <assay>GSM533951</assay>
                            <assay>GSM533975</assay>
                            <assay>GSM534020</assay>
                            <assay>GSM533995</assay>
                            <assay>GSM534162</assay>
                            <assay>GSM533959</assay>
                            <assay>GSM534008</assay>
                            <assay>GSM533931</assay>
                        </batch>
                    </batch_effect>
                </batch_effects>
            </contrast>
        </contrasts>
    </analytics>
</configuration>
