<?xml version="1.0" encoding="UTF-8"?>

<configuration experimentType="microarray_1colour_mrna_differential" r_data="1">
    <analytics>
        <array_design>A-AFFY-44</array_design>
        <assay_groups>
            <assay_group id="g1" label="normal">
                <assay>GSM404131</assay>
                <assay>GSM404105</assay>
                <assay>GSM404134</assay>
                <assay>GSM404242</assay>
                <assay>GSM404085</assay>
                <assay>GSM404036</assay>
                <assay>GSM404160</assay>
                <assay>GSM404251</assay>
                <assay>GSM404149</assay>
                <assay>GSM404102</assay>
                <assay>GSM404225</assay>
                <assay>GSM404093</assay>
                <assay>GSM404236</assay>
                <assay>GSM404074</assay>
                <assay>GSM404222</assay>
                <assay>GSM404152</assay>
                <assay>GSM404088</assay>
                <assay>GSM404270</assay>
                <assay>GSM404183</assay>
                <assay>GSM404016</assay>
                <assay>GSM404053</assay>
                <assay>GSM404273</assay>
                <assay>GSM404108</assay>
                <assay>GSM404025</assay>
                <assay>GSM404180</assay>
                <assay>GSM404075</assay>
                <assay>GSM404117</assay>
                <assay>GSM404172</assay>
                <assay>GSM404013</assay>
                <assay>GSM404169</assay>
                <assay>GSM404206</assay>
                <assay>GSM404071</assay>
                <assay>GSM404284</assay>
                <assay>GSM404080</assay>
                <assay>GSM404260</assay>
                <assay>GSM404239</assay>
                <assay>GSM404190</assay>
                <assay>GSM404248</assay>
                <assay>GSM404166</assay>
                <assay>GSM404096</assay>
                <assay>GSM404203</assay>
                <assay>GSM404064</assay>
                <assay>GSM404049</assay>
                <assay>GSM404031</assay>
                <assay>GSM404143</assay>
                <assay>GSM404228</assay>
                <assay>GSM404099</assay>
                <assay>GSM404155</assay>
                <assay>GSM404115</assay>
                <assay>GSM404233</assay>
                <assay>GSM404054</assay>
                <assay>GSM404007</assay>
                <assay>GSM404128</assay>
                <assay>GSM404039</assay>
                <assay>GSM404017</assay>
                <assay>GSM404146</assay>
                <assay>GSM404245</assay>
                <assay>GSM404028</assay>
                <assay>GSM404042</assay>
                <assay>GSM404163</assay>
                <assay>GSM404195</assay>
                <assay>GSM404010</assay>
                <assay>GSM404175</assay>
                <assay>GSM404267</assay>
                <assay>GSM404122</assay>
                <assay>GSM404200</assay>
                <assay>GSM404059</assay>
                <assay>GSM404215</assay>
                <assay>GSM404125</assay>
            </assay_group>
            <assay_group id="g2" label="periodontitis">
                <assay>GSM404304</assay>
                <assay>GSM404207</assay>
                <assay>GSM404241</assay>
                <assay>GSM404023</assay>
                <assay>GSM404034</assay>
                <assay>GSM404279</assay>
                <assay>GSM404286</assay>
                <assay>GSM404189</assay>
                <assay>GSM404106</assay>
                <assay>GSM404259</assay>
                <assay>GSM404287</assay>
                <assay>GSM404294</assay>
                <assay>GSM404065</assay>
                <assay>GSM404238</assay>
                <assay>GSM404303</assay>
                <assay>GSM404177</assay>
                <assay>GSM404148</assay>
                <assay>GSM404018</assay>
                <assay>GSM404205</assay>
                <assay>GSM404224</assay>
                <assay>GSM404026</assay>
                <assay>GSM404113</assay>
                <assay>GSM404192</assay>
                <assay>GSM404035</assay>
                <assay>GSM404055</assay>
                <assay>GSM404199</assay>
                <assay>GSM404301</assay>
                <assay>GSM404226</assay>
                <assay>GSM404274</assay>
                <assay>GSM404167</assay>
                <assay>GSM404185</assay>
                <assay>GSM404047</assay>
                <assay>GSM404027</assay>
                <assay>GSM404221</assay>
                <assay>GSM404210</assay>
                <assay>GSM404012</assay>
                <assay>GSM404209</assay>
                <assay>GSM404171</assay>
                <assay>GSM404249</assay>
                <assay>GSM404230</assay>
                <assay>GSM404204</assay>
                <assay>GSM404045</assay>
                <assay>GSM404216</assay>
                <assay>GSM404295</assay>
                <assay>GSM404194</assay>
                <assay>GSM404257</assay>
                <assay>GSM404015</assay>
                <assay>GSM404179</assay>
                <assay>GSM404291</assay>
                <assay>GSM404174</assay>
                <assay>GSM404240</assay>
                <assay>GSM404041</assay>
                <assay>GSM404044</assay>
                <assay>GSM404299</assay>
                <assay>GSM404132</assay>
                <assay>GSM404197</assay>
                <assay>GSM404302</assay>
                <assay>GSM404056</assay>
                <assay>GSM404147</assay>
                <assay>GSM404107</assay>
                <assay>GSM404082</assay>
                <assay>GSM404121</assay>
                <assay>GSM404094</assay>
                <assay>GSM404063</assay>
                <assay>GSM404156</assay>
                <assay>GSM404144</assay>
                <assay>GSM404314</assay>
                <assay>GSM404124</assay>
                <assay>GSM404050</assay>
                <assay>GSM404276</assay>
                <assay>GSM404092</assay>
                <assay>GSM404048</assay>
                <assay>GSM404029</assay>
                <assay>GSM404292</assay>
                <assay>GSM404264</assay>
                <assay>GSM404165</assay>
                <assay>GSM404011</assay>
                <assay>GSM404220</assay>
                <assay>GSM404272</assay>
                <assay>GSM404293</assay>
                <assay>GSM404077</assay>
                <assay>GSM404019</assay>
                <assay>GSM404305</assay>
                <assay>GSM404021</assay>
                <assay>GSM404191</assay>
                <assay>GSM404030</assay>
                <assay>GSM404237</assay>
                <assay>GSM404079</assay>
                <assay>GSM404137</assay>
                <assay>GSM404083</assay>
                <assay>GSM404114</assay>
                <assay>GSM404009</assay>
                <assay>GSM404271</assay>
                <assay>GSM404263</assay>
                <assay>GSM404157</assay>
                <assay>GSM404084</assay>
                <assay>GSM404069</assay>
                <assay>GSM404091</assay>
                <assay>GSM404244</assay>
                <assay>GSM404022</assay>
                <assay>GSM404285</assay>
                <assay>GSM404040</assay>
                <assay>GSM404032</assay>
                <assay>GSM404123</assay>
                <assay>GSM404089</assay>
                <assay>GSM404154</assay>
                <assay>GSM404310</assay>
                <assay>GSM404142</assay>
                <assay>GSM404008</assay>
                <assay>GSM404103</assay>
                <assay>GSM404101</assay>
                <assay>GSM404256</assay>
                <assay>GSM404038</assay>
                <assay>GSM404127</assay>
                <assay>GSM404133</assay>
                <assay>GSM404255</assay>
                <assay>GSM404087</assay>
                <assay>GSM404068</assay>
                <assay>GSM404057</assay>
                <assay>GSM404218</assay>
                <assay>GSM404020</assay>
                <assay>GSM404086</assay>
                <assay>GSM404033</assay>
                <assay>GSM404150</assay>
                <assay>GSM404139</assay>
                <assay>GSM404095</assay>
                <assay>GSM404145</assay>
                <assay>GSM404281</assay>
                <assay>GSM404164</assay>
                <assay>GSM404130</assay>
                <assay>GSM404078</assay>
                <assay>GSM404090</assay>
                <assay>GSM404246</assay>
                <assay>GSM404158</assay>
                <assay>GSM404006</assay>
                <assay>GSM404104</assay>
                <assay>GSM404061</assay>
                <assay>GSM404081</assay>
                <assay>GSM404111</assay>
                <assay>GSM404253</assay>
                <assay>GSM404223</assay>
                <assay>GSM404306</assay>
                <assay>GSM404176</assay>
                <assay>GSM404198</assay>
                <assay>GSM404070</assay>
                <assay>GSM404254</assay>
                <assay>GSM404051</assay>
                <assay>GSM404312</assay>
                <assay>GSM404262</assay>
                <assay>GSM404229</assay>
                <assay>GSM404178</assay>
                <assay>GSM404126</assay>
                <assay>GSM404141</assay>
                <assay>GSM404116</assay>
                <assay>GSM404307</assay>
                <assay>GSM404153</assay>
                <assay>GSM404309</assay>
                <assay>GSM404235</assay>
                <assay>GSM404300</assay>
                <assay>GSM404196</assay>
                <assay>GSM404186</assay>
                <assay>GSM404110</assay>
                <assay>GSM404298</assay>
                <assay>GSM404066</assay>
                <assay>GSM404129</assay>
                <assay>GSM404188</assay>
                <assay>GSM404278</assay>
                <assay>GSM404138</assay>
                <assay>GSM404308</assay>
                <assay>GSM404118</assay>
                <assay>GSM404161</assay>
                <assay>GSM404151</assay>
                <assay>GSM404288</assay>
                <assay>GSM404014</assay>
                <assay>GSM404193</assay>
                <assay>GSM404250</assay>
                <assay>GSM404214</assay>
                <assay>GSM404277</assay>
                <assay>GSM404243</assay>
                <assay>GSM404283</assay>
                <assay>GSM404052</assay>
                <assay>GSM404046</assay>
                <assay>GSM404173</assay>
                <assay>GSM404266</assay>
                <assay>GSM404227</assay>
                <assay>GSM404109</assay>
                <assay>GSM404043</assay>
                <assay>GSM404098</assay>
                <assay>GSM404067</assay>
                <assay>GSM404296</assay>
                <assay>GSM404100</assay>
                <assay>GSM404058</assay>
                <assay>GSM404252</assay>
                <assay>GSM404261</assay>
                <assay>GSM404072</assay>
                <assay>GSM404247</assay>
                <assay>GSM404289</assay>
                <assay>GSM404290</assay>
                <assay>GSM404297</assay>
                <assay>GSM404313</assay>
                <assay>GSM404062</assay>
                <assay>GSM404005</assay>
                <assay>GSM404170</assay>
                <assay>GSM404269</assay>
                <assay>GSM404181</assay>
                <assay>GSM404275</assay>
                <assay>GSM404168</assay>
                <assay>GSM404258</assay>
                <assay>GSM404265</assay>
                <assay>GSM404208</assay>
                <assay>GSM404219</assay>
                <assay>GSM404213</assay>
                <assay>GSM404135</assay>
                <assay>GSM404060</assay>
                <assay>GSM404097</assay>
                <assay>GSM404232</assay>
                <assay>GSM404187</assay>
                <assay>GSM404112</assay>
                <assay>GSM404024</assay>
                <assay>GSM404201</assay>
                <assay>GSM404120</assay>
                <assay>GSM404231</assay>
                <assay>GSM404076</assay>
                <assay>GSM404182</assay>
                <assay>GSM404037</assay>
                <assay>GSM404311</assay>
                <assay>GSM404162</assay>
                <assay>GSM404073</assay>
                <assay>GSM404268</assay>
                <assay>GSM404282</assay>
                <assay>GSM404280</assay>
                <assay>GSM404119</assay>
                <assay>GSM404211</assay>
                <assay>GSM404212</assay>
                <assay>GSM404202</assay>
                <assay>GSM404184</assay>
                <assay>GSM404234</assay>
                <assay>GSM404159</assay>
                <assay>GSM404136</assay>
                <assay>GSM404140</assay>
            </assay_group>
        </assay_groups>
        <contrasts>
            <contrast id="g1_g2" cttv_primary="1">
                <name>'periodontitis' vs 'normal'</name>
                <reference_assay_group>g1</reference_assay_group>
                <test_assay_group>g2</test_assay_group>
            </contrast>
        </contrasts>
    </analytics>
</configuration>
